MHRParse/MHRParse.py
MHRParse/__init__.py
mhrparse-0.0.1.dist-info/METADATA
mhrparse-0.0.1.dist-info/WHEEL
mhrparse-0.0.1.dist-info/RECORD
