Metadata-Version: 2.1
Name: MHRParse
Version: 0.0.1
Summary: Package for converting .mhr to .json and vice versa
Project-URL: Homepage, https://github.com/5Litt/MHRParse
Classifier: License :: OSI Approved :: MIT License
Classifier: Operating System :: OS Independent
Classifier: Programming Language :: Python :: 3
Requires-Python: >=3.7
